technic/__init__.py
technic/technic.py
technic-0.0.3.dist-info/LICENSE
technic-0.0.3.dist-info/METADATA
technic-0.0.3.dist-info/WHEEL
technic-0.0.3.dist-info/top_level.txt
technic-0.0.3.dist-info/RECORD
