Metadata-Version: 2.1
Name: technic
Version: 0.0.3
Summary: A python library for Technical Trading
Home-page: https://github.com/dvd9604/technic.git
Author: Divyaansh Dandona
Author-email: divy96@gmail.com
License: UNKNOWN
Keywords: trading,technical,analysis
Platform: UNKNOWN
Classifier: Programming Language :: Python :: 3
Classifier: License :: OSI Approved :: MIT License
Classifier: Operating System :: OS Independent
Requires-Python: >=3.5
